PyCycle_bio/PyCycle.py
PyCycle_bio/__init__.py
PyCycle_bio-0.0.4.dist-info/LICENSE.txt
PyCycle_bio-0.0.4.dist-info/METADATA
PyCycle_bio-0.0.4.dist-info/WHEEL
PyCycle_bio-0.0.4.dist-info/top_level.txt
PyCycle_bio-0.0.4.dist-info/RECORD
